[
  {
    "Date":1738040400000,
    "Close":19.75,
    "Dividends":0.0,
    "Stock Splits":0.0
  },
  {
    "Date":1738126800000,
    "Close":20.4899997711,
    "Dividends":0.0,
    "Stock Splits":0.0
  },
  {
    "Date":1738213200000,
    "Close":21.7900009155,
    "Dividends":0.0,
    "Stock Splits":0.0
  },
  {
    "Date":1738299600000,
    "Close":21.5,
    "Dividends":0.0,
    "Stock Splits":0.0
  },
  {
    "Date":1738558800000,
    "Close":21.8199996948,
    "Dividends":0.0,
    "Stock Splits":0.0
  },
  {
    "Date":1738645200000,
    "Close":21.4799995422,
    "Dividends":0.0,
    "Stock Splits":0.0
  },
  {
    "Date":1738731600000,
    "Close":21.1299991608,
    "Dividends":0.0,
    "Stock Splits":0.0
  },
  {
    "Date":1738818000000,
    "Close":20.7000007629,
    "Dividends":0.0,
    "Stock Splits":0.0
  },
  {
    "Date":1738904400000,
    "Close":21.1200008392,
    "Dividends":0.0,
    "Stock Splits":0.0
  },
  {
    "Date":1739163600000,
    "Close":21.2600002289,
    "Dividends":0.0,
    "Stock Splits":0.0
  },
  {
    "Date":1739250000000,
    "Close":21.2600002289,
    "Dividends":0.0,
    "Stock Splits":0.0
  },
  {
    "Date":1739336400000,
    "Close":21.5,
    "Dividends":0.0,
    "Stock Splits":0.0
  },
  {
    "Date":1739422800000,
    "Close":21.1800003052,
    "Dividends":0.0,
    "Stock Splits":0.0
  },
  {
    "Date":1739509200000,
    "Close":21.2299995422,
    "Dividends":0.0,
    "Stock Splits":0.0
  },
  {
    "Date":1739854800000,
    "Close":21.4400005341,
    "Dividends":0.0,
    "Stock Splits":0.0
  },
  {
    "Date":1739941200000,
    "Close":21.4699993134,
    "Dividends":0.0,
    "Stock Splits":0.0
  },
  {
    "Date":1740027600000,
    "Close":21.2999992371,
    "Dividends":0.0,
    "Stock Splits":0.0
  },
  {
    "Date":1740114000000,
    "Close":21.1000003815,
    "Dividends":0.0,
    "Stock Splits":0.0
  },
  {
    "Date":1740373200000,
    "Close":21.3400001526,
    "Dividends":0.0,
    "Stock Splits":0.0
  },
  {
    "Date":1740459600000,
    "Close":21.6000003815,
    "Dividends":0.0,
    "Stock Splits":0.0
  },
  {
    "Date":1740546000000,
    "Close":20.6000003815,
    "Dividends":0.0,
    "Stock Splits":0.0
  },
  {
    "Date":1740632400000,
    "Close":21.0100002289,
    "Dividends":0.0,
    "Stock Splits":0.0
  },
  {
    "Date":1740718800000,
    "Close":20.8400001526,
    "Dividends":0.0,
    "Stock Splits":0.0
  },
  {
    "Date":1740978000000,
    "Close":20.8700008392,
    "Dividends":0.0,
    "Stock Splits":0.0
  },
  {
    "Date":1741064400000,
    "Close":19.7700004578,
    "Dividends":0.0,
    "Stock Splits":0.0
  },
  {
    "Date":1741150800000,
    "Close":20.3299999237,
    "Dividends":0.0,
    "Stock Splits":0.0
  },
  {
    "Date":1741237200000,
    "Close":19.7700004578,
    "Dividends":0.0,
    "Stock Splits":0.0
  },
  {
    "Date":1741323600000,
    "Close":19.2999992371,
    "Dividends":0.0,
    "Stock Splits":0.0
  },
  {
    "Date":1741579200000,
    "Close":18.6100006104,
    "Dividends":0.0,
    "Stock Splits":0.0
  },
  {
    "Date":1741665600000,
    "Close":19.2600002289,
    "Dividends":0.0,
    "Stock Splits":0.0
  },
  {
    "Date":1741752000000,
    "Close":19.3299999237,
    "Dividends":0.0,
    "Stock Splits":0.0
  },
  {
    "Date":1741838400000,
    "Close":18.9799995422,
    "Dividends":0.0,
    "Stock Splits":0.0
  },
  {
    "Date":1741924800000,
    "Close":19.0200004578,
    "Dividends":0.0,
    "Stock Splits":0.0
  },
  {
    "Date":1742184000000,
    "Close":19.5400009155,
    "Dividends":0.0,
    "Stock Splits":0.0
  },
  {
    "Date":1742270400000,
    "Close":20.0100002289,
    "Dividends":0.0,
    "Stock Splits":0.0
  },
  {
    "Date":1742356800000,
    "Close":19.7800006866,
    "Dividends":0.0,
    "Stock Splits":0.0
  },
  {
    "Date":1742443200000,
    "Close":19.6499996185,
    "Dividends":0.0,
    "Stock Splits":0.0
  },
  {
    "Date":1742529600000,
    "Close":19.0499992371,
    "Dividends":0.0,
    "Stock Splits":0.0
  },
  {
    "Date":1742788800000,
    "Close":19.6000003815,
    "Dividends":0.0,
    "Stock Splits":0.0
  }
]