[
  {
    "Date":1688011200000,
    "Close":14.3732509613,
    "Dividends":0.0,
    "Stock Splits":0.0
  },
  {
    "Date":1688097600000,
    "Close":14.8676166534,
    "Dividends":0.0,
    "Stock Splits":0.0
  },
  {
    "Date":1688356800000,
    "Close":14.5563497543,
    "Dividends":0.0,
    "Stock Splits":0.0
  },
  {
    "Date":1688529600000,
    "Close":14.0070533752,
    "Dividends":0.0,
    "Stock Splits":0.0
  },
  {
    "Date":1688616000000,
    "Close":14.6845197678,
    "Dividends":0.0,
    "Stock Splits":0.0
  },
  {
    "Date":1688702400000,
    "Close":14.647898674,
    "Dividends":0.0,
    "Stock Splits":0.0
  },
  {
    "Date":1688961600000,
    "Close":14.7302942276,
    "Dividends":0.0,
    "Stock Splits":0.0
  },
  {
    "Date":1689048000000,
    "Close":14.8126878738,
    "Dividends":0.0,
    "Stock Splits":0.0
  },
  {
    "Date":1689134400000,
    "Close":14.7119827271,
    "Dividends":0.0,
    "Stock Splits":0.0
  },
  {
    "Date":1689220800000,
    "Close":14.9225463867,
    "Dividends":0.0,
    "Stock Splits":0.0
  },
  {
    "Date":1689307200000,
    "Close":14.8676166534,
    "Dividends":0.0,
    "Stock Splits":0.0
  },
  {
    "Date":1689566400000,
    "Close":14.9042387009,
    "Dividends":0.0,
    "Stock Splits":0.0
  },
  {
    "Date":1689652800000,
    "Close":15.0415611267,
    "Dividends":0.0,
    "Stock Splits":0.0
  },
  {
    "Date":1689739200000,
    "Close":15.1514196396,
    "Dividends":0.0,
    "Stock Splits":0.0
  },
  {
    "Date":1689825600000,
    "Close":15.4077587128,
    "Dividends":0.0,
    "Stock Splits":0.0
  },
  {
    "Date":1689912000000,
    "Close":15.6915607452,
    "Dividends":0.0,
    "Stock Splits":0.0
  },
  {
    "Date":1690171200000,
    "Close":15.7281808853,
    "Dividends":0.0,
    "Stock Splits":0.0
  },
  {
    "Date":1690257600000,
    "Close":16.4971961975,
    "Dividends":0.0,
    "Stock Splits":0.0
  },
  {
    "Date":1690344000000,
    "Close":16.2957878113,
    "Dividends":0.0,
    "Stock Splits":0.0
  },
  {
    "Date":1690430400000,
    "Close":16.6894493103,
    "Dividends":0.0,
    "Stock Splits":0.0
  },
  {
    "Date":1690516800000,
    "Close":17.3669166565,
    "Dividends":0.0,
    "Stock Splits":0.0
  },
  {
    "Date":1690776000000,
    "Close":17.1197319031,
    "Dividends":0.0,
    "Stock Splits":0.0
  },
  {
    "Date":1690862400000,
    "Close":17.1105766296,
    "Dividends":0.0,
    "Stock Splits":0.0
  },
  {
    "Date":1690948800000,
    "Close":17.0556468964,
    "Dividends":0.0,
    "Stock Splits":0.0
  },
  {
    "Date":1691035200000,
    "Close":17.412689209,
    "Dividends":0.0,
    "Stock Splits":0.0
  },
  {
    "Date":1691121600000,
    "Close":17.5408592224,
    "Dividends":0.0,
    "Stock Splits":0.0
  },
  {
    "Date":1691380800000,
    "Close":17.1014232635,
    "Dividends":0.0,
    "Stock Splits":0.0
  },
  {
    "Date":1691467200000,
    "Close":17.0373363495,
    "Dividends":0.0,
    "Stock Splits":0.0
  },
  {
    "Date":1691553600000,
    "Close":17.4950866699,
    "Dividends":0.0,
    "Stock Splits":0.0
  },
  {
    "Date":1691640000000,
    "Close":17.2478981018,
    "Dividends":0.0,
    "Stock Splits":0.0
  },
  {
    "Date":1691726400000,
    "Close":17.7148017883,
    "Dividends":0.0,
    "Stock Splits":0.0
  },
  {
    "Date":1691985600000,
    "Close":17.9619846344,
    "Dividends":0.0,
    "Stock Splits":0.0
  },
  {
    "Date":1692072000000,
    "Close":17.2845172882,
    "Dividends":0.0,
    "Stock Splits":0.0
  },
  {
    "Date":1692158400000,
    "Close":17.4676189423,
    "Dividends":0.0,
    "Stock Splits":0.0
  },
  {
    "Date":1692244800000,
    "Close":17.5683231354,
    "Dividends":0.0,
    "Stock Splits":0.0
  },
  {
    "Date":1692331200000,
    "Close":17.4859294891,
    "Dividends":0.0,
    "Stock Splits":0.0
  },
  {
    "Date":1692590400000,
    "Close":17.0648040771,
    "Dividends":0.0,
    "Stock Splits":0.0
  },
  {
    "Date":1692676800000,
    "Close":16.7626895905,
    "Dividends":0.0,
    "Stock Splits":0.0
  },
  {
    "Date":1692763200000,
    "Close":16.515504837,
    "Dividends":0.0,
    "Stock Splits":0.0
  },
  {
    "Date":1692849600000,
    "Close":16.5246601105,
    "Dividends":0.0,
    "Stock Splits":0.0
  },
  {
    "Date":1692936000000,
    "Close":16.634519577,
    "Dividends":0.0,
    "Stock Splits":0.0
  },
  {
    "Date":1693195200000,
    "Close":16.7260704041,
    "Dividends":0.0,
    "Stock Splits":0.0
  },
  {
    "Date":1693281600000,
    "Close":16.387336731,
    "Dividends":0.0,
    "Stock Splits":0.0
  },
  {
    "Date":1693368000000,
    "Close":16.6802959442,
    "Dividends":0.0,
    "Stock Splits":0.0
  },
  {
    "Date":1693454400000,
    "Close":16.7443790436,
    "Dividends":0.0,
    "Stock Splits":0.0
  },
  {
    "Date":1693540800000,
    "Close":16.9183216095,
    "Dividends":0.0,
    "Stock Splits":0.0
  },
  {
    "Date":1693886400000,
    "Close":16.4422645569,
    "Dividends":0.0,
    "Stock Splits":0.0
  },
  {
    "Date":1693972800000,
    "Close":16.4239578247,
    "Dividends":0.0,
    "Stock Splits":0.0
  },
  {
    "Date":1694059200000,
    "Close":16.4239578247,
    "Dividends":0.0,
    "Stock Splits":0.0
  },
  {
    "Date":1694145600000,
    "Close":16.2774791718,
    "Dividends":0.0,
    "Stock Splits":0.0
  },
  {
    "Date":1694404800000,
    "Close":15.9295911789,
    "Dividends":0.0,
    "Stock Splits":0.0
  },
  {
    "Date":1694491200000,
    "Close":16.6070556641,
    "Dividends":0.0,
    "Stock Splits":0.0
  },
  {
    "Date":1694577600000,
    "Close":16.2133922577,
    "Dividends":0.0,
    "Stock Splits":0.0
  },
  {
    "Date":1694664000000,
    "Close":16.515504837,
    "Dividends":0.0,
    "Stock Splits":0.0
  },
  {
    "Date":1694750400000,
    "Close":16.3140983582,
    "Dividends":0.0,
    "Stock Splits":0.0
  },
  {
    "Date":1695009600000,
    "Close":16.6802959442,
    "Dividends":0.0,
    "Stock Splits":0.0
  },
  {
    "Date":1695096000000,
    "Close":16.1126880646,
    "Dividends":0.0,
    "Stock Splits":0.0
  },
  {
    "Date":1695182400000,
    "Close":16.0119838715,
    "Dividends":0.0,
    "Stock Splits":0.0
  },
  {
    "Date":1695268800000,
    "Close":15.7739572525,
    "Dividends":0.0,
    "Stock Splits":0.0
  },
  {
    "Date":1695355200000,
    "Close":16.149307251,
    "Dividends":0.0,
    "Stock Splits":0.0
  },
  {
    "Date":1695614400000,
    "Close":16.2683238983,
    "Dividends":0.0,
    "Stock Splits":0.0
  },
  {
    "Date":1695700800000,
    "Close":16.1401538849,
    "Dividends":0.0,
    "Stock Splits":0.0
  },
  {
    "Date":1695787200000,
    "Close":16.8084640503,
    "Dividends":0.0,
    "Stock Splits":0.0
  },
  {
    "Date":1695873600000,
    "Close":16.7901554108,
    "Dividends":0.0,
    "Stock Splits":0.0
  },
  {
    "Date":1695960000000,
    "Close":16.3690280914,
    "Dividends":0.0,
    "Stock Splits":0.0
  },
  {
    "Date":1696219200000,
    "Close":15.9845180511,
    "Dividends":0.0,
    "Stock Splits":0.0
  },
  {
    "Date":1696305600000,
    "Close":16.1859283447,
    "Dividends":0.0,
    "Stock Splits":0.0
  },
  {
    "Date":1696392000000,
    "Close":15.7373371124,
    "Dividends":0.0,
    "Stock Splits":0.0
  },
  {
    "Date":1696478400000,
    "Close":15.7922668457,
    "Dividends":0.0,
    "Stock Splits":0.0
  },
  {
    "Date":1696564800000,
    "Close":15.911280632,
    "Dividends":0.0,
    "Stock Splits":0.0
  },
  {
    "Date":1696824000000,
    "Close":16.2225494385,
    "Dividends":0.0,
    "Stock Splits":0.0
  },
  {
    "Date":1696910400000,
    "Close":16.4605731964,
    "Dividends":0.0,
    "Stock Splits":0.0
  },
  {
    "Date":1696996800000,
    "Close":16.4422645569,
    "Dividends":0.0,
    "Stock Splits":0.0
  },
  {
    "Date":1697083200000,
    "Close":16.2408561707,
    "Dividends":0.0,
    "Stock Splits":0.0
  },
  {
    "Date":1697169600000,
    "Close":16.359872818,
    "Dividends":0.0,
    "Stock Splits":0.0
  },
  {
    "Date":1697428800000,
    "Close":16.0486049652,
    "Dividends":0.0,
    "Stock Splits":0.0
  },
  {
    "Date":1697515200000,
    "Close":15.8746595383,
    "Dividends":0.0,
    "Stock Splits":0.0
  },
  {
    "Date":1697601600000,
    "Close":15.9570531845,
    "Dividends":0.0,
    "Stock Splits":0.0
  },
  {
    "Date":1697688000000,
    "Close":15.8380393982,
    "Dividends":0.0,
    "Stock Splits":0.0
  },
  {
    "Date":1697774400000,
    "Close":15.7556447983,
    "Dividends":0.0,
    "Stock Splits":0.0
  },
  {
    "Date":1698033600000,
    "Close":15.6000137329,
    "Dividends":0.0,
    "Stock Splits":0.0
  },
  {
    "Date":1698120000000,
    "Close":15.5359268188,
    "Dividends":0.0,
    "Stock Splits":0.0
  },
  {
    "Date":1698206400000,
    "Close":15.8838157654,
    "Dividends":0.0,
    "Stock Splits":0.0
  },
  {
    "Date":1698292800000,
    "Close":15.9204330444,
    "Dividends":0.0,
    "Stock Splits":0.0
  },
  {
    "Date":1698379200000,
    "Close":15.7464904785,
    "Dividends":0.0,
    "Stock Splits":0.0
  },
  {
    "Date":1698638400000,
    "Close":15.6824064255,
    "Dividends":0.0,
    "Stock Splits":0.0
  },
  {
    "Date":1698724800000,
    "Close":15.7373371124,
    "Dividends":0.0,
    "Stock Splits":0.0
  },
  {
    "Date":1698811200000,
    "Close":15.7190294266,
    "Dividends":0.0,
    "Stock Splits":0.0
  },
  {
    "Date":1698897600000,
    "Close":16.1777706146,
    "Dividends":0.38,
    "Stock Splits":0.0
  },
  {
    "Date":1698984000000,
    "Close":16.3743743896,
    "Dividends":0.0,
    "Stock Splits":0.0
  },
  {
    "Date":1699246800000,
    "Close":16.0560626984,
    "Dividends":0.0,
    "Stock Splits":0.0
  },
  {
    "Date":1699333200000,
    "Close":16.0186138153,
    "Dividends":0.0,
    "Stock Splits":0.0
  },
  {
    "Date":1699419600000,
    "Close":15.7377510071,
    "Dividends":0.0,
    "Stock Splits":0.0
  },
  {
    "Date":1699506000000,
    "Close":15.9437179565,
    "Dividends":0.0,
    "Stock Splits":0.0
  },
  {
    "Date":1699592400000,
    "Close":16.5428943634,
    "Dividends":0.0,
    "Stock Splits":0.0
  },
  {
    "Date":1699851600000,
    "Close":16.6177921295,
    "Dividends":0.0,
    "Stock Splits":0.0
  },
  {
    "Date":1699938000000,
    "Close":16.9735546112,
    "Dividends":0.0,
    "Stock Splits":0.0
  },
  {
    "Date":1700024400000,
    "Close":16.7394981384,
    "Dividends":0.0,
    "Stock Splits":0.0
  },
  {
    "Date":1700110800000,
    "Close":16.7114105225,
    "Dividends":0.0,
    "Stock Splits":0.0
  },
  {
    "Date":1700197200000,
    "Close":17.1327056885,
    "Dividends":0.0,
    "Stock Splits":0.0
  },
  {
    "Date":1700456400000,
    "Close":17.2544174194,
    "Dividends":0.0,
    "Stock Splits":0.0
  },
  {
    "Date":1700542800000,
    "Close":17.1327056885,
    "Dividends":0.0,
    "Stock Splits":0.0
  },
  {
    "Date":1700629200000,
    "Close":17.1420726776,
    "Dividends":0.0,
    "Stock Splits":0.0
  },
  {
    "Date":1700802000000,
    "Close":17.216966629,
    "Dividends":0.0,
    "Stock Splits":0.0
  },
  {
    "Date":1701061200000,
    "Close":17.0858974457,
    "Dividends":0.0,
    "Stock Splits":0.0
  },
  {
    "Date":1701147600000,
    "Close":16.8237571716,
    "Dividends":0.0,
    "Stock Splits":0.0
  },
  {
    "Date":1701234000000,
    "Close":16.767583847,
    "Dividends":0.0,
    "Stock Splits":0.0
  },
  {
    "Date":1701320400000,
    "Close":16.5054473877,
    "Dividends":0.0,
    "Stock Splits":0.0
  },
  {
    "Date":1701406800000,
    "Close":16.6271533966,
    "Dividends":0.0,
    "Stock Splits":0.0
  },
  {
    "Date":1701666000000,
    "Close":17.2076053619,
    "Dividends":0.0,
    "Stock Splits":0.0
  },
  {
    "Date":1701752400000,
    "Close":16.9267425537,
    "Dividends":0.0,
    "Stock Splits":0.0
  },
  {
    "Date":1701838800000,
    "Close":16.7956733704,
    "Dividends":0.0,
    "Stock Splits":0.0
  },
  {
    "Date":1701925200000,
    "Close":16.8143959045,
    "Dividends":0.0,
    "Stock Splits":0.0
  },
  {
    "Date":1702011600000,
    "Close":17.1795196533,
    "Dividends":0.0,
    "Stock Splits":0.0
  },
  {
    "Date":1702270800000,
    "Close":16.8237571716,
    "Dividends":0.0,
    "Stock Splits":0.0
  },
  {
    "Date":1702357200000,
    "Close":16.7207756042,
    "Dividends":0.0,
    "Stock Splits":0.0
  },
  {
    "Date":1702443600000,
    "Close":16.9454650879,
    "Dividends":0.0,
    "Stock Splits":0.0
  },
  {
    "Date":1702530000000,
    "Close":17.4042110443,
    "Dividends":0.0,
    "Stock Splits":0.0
  },
  {
    "Date":1702616400000,
    "Close":17.3761253357,
    "Dividends":0.0,
    "Stock Splits":0.0
  },
  {
    "Date":1702875600000,
    "Close":17.9097652435,
    "Dividends":0.0,
    "Stock Splits":0.0
  },
  {
    "Date":1702962000000,
    "Close":18.3778705597,
    "Dividends":0.0,
    "Stock Splits":0.0
  },
  {
    "Date":1703048400000,
    "Close":18.2655296326,
    "Dividends":0.0,
    "Stock Splits":0.0
  },
  {
    "Date":1703134800000,
    "Close":18.4621315002,
    "Dividends":0.0,
    "Stock Splits":0.0
  },
  {
    "Date":1703221200000,
    "Close":18.4621315002,
    "Dividends":0.0,
    "Stock Splits":0.0
  },
  {
    "Date":1703566800000,
    "Close":18.9302368164,
    "Dividends":0.0,
    "Stock Splits":0.0
  },
  {
    "Date":1703653200000,
    "Close":19.05194664,
    "Dividends":0.0,
    "Stock Splits":0.0
  },
  {
    "Date":1703739600000,
    "Close":18.8178939819,
    "Dividends":0.0,
    "Stock Splits":0.0
  },
  {
    "Date":1703826000000,
    "Close":18.7991695404,
    "Dividends":0.0,
    "Stock Splits":0.0
  },
  {
    "Date":1704171600000,
    "Close":18.8927898407,
    "Dividends":0.0,
    "Stock Splits":0.0
  },
  {
    "Date":1704258000000,
    "Close":19.2579135895,
    "Dividends":0.0,
    "Stock Splits":0.0
  },
  {
    "Date":1704344400000,
    "Close":18.9957752228,
    "Dividends":0.0,
    "Stock Splits":0.0
  },
  {
    "Date":1704430800000,
    "Close":19.9787979126,
    "Dividends":0.0,
    "Stock Splits":0.0
  },
  {
    "Date":1704690000000,
    "Close":19.7821922302,
    "Dividends":0.0,
    "Stock Splits":0.0
  },
  {
    "Date":1704776400000,
    "Close":19.8664512634,
    "Dividends":0.0,
    "Stock Splits":0.0
  },
  {
    "Date":1704862800000,
    "Close":19.2953624725,
    "Dividends":0.0,
    "Stock Splits":0.0
  },
  {
    "Date":1704949200000,
    "Close":19.5668640137,
    "Dividends":0.0,
    "Stock Splits":0.0
  },
  {
    "Date":1705035600000,
    "Close":20.0630588531,
    "Dividends":0.0,
    "Stock Splits":0.0
  },
  {
    "Date":1705381200000,
    "Close":19.9694366455,
    "Dividends":0.0,
    "Stock Splits":0.0
  },
  {
    "Date":1705467600000,
    "Close":19.9600734711,
    "Dividends":0.0,
    "Stock Splits":0.0
  },
  {
    "Date":1705554000000,
    "Close":20.2596626282,
    "Dividends":0.0,
    "Stock Splits":0.0
  },
  {
    "Date":1705640400000,
    "Close":20.2971115112,
    "Dividends":0.0,
    "Stock Splits":0.0
  },
  {
    "Date":1705899600000,
    "Close":20.6996822357,
    "Dividends":0.0,
    "Stock Splits":0.0
  },
  {
    "Date":1705986000000,
    "Close":20.9899082184,
    "Dividends":0.0,
    "Stock Splits":0.0
  },
  {
    "Date":1706072400000,
    "Close":21.280134201,
    "Dividends":0.0,
    "Stock Splits":0.0
  },
  {
    "Date":1706158800000,
    "Close":21.6452579498,
    "Dividends":0.0,
    "Stock Splits":0.0
  },
  {
    "Date":1706245200000,
    "Close":21.9448471069,
    "Dividends":0.0,
    "Stock Splits":0.0
  },
  {
    "Date":1706504400000,
    "Close":22.1508140564,
    "Dividends":0.0,
    "Stock Splits":0.0
  },
  {
    "Date":1706590800000,
    "Close":22.244436264,
    "Dividends":0.0,
    "Stock Splits":0.0
  },
  {
    "Date":1706677200000,
    "Close":21.9261226654,
    "Dividends":0.0,
    "Stock Splits":0.0
  },
  {
    "Date":1706763600000,
    "Close":21.7388801575,
    "Dividends":0.0,
    "Stock Splits":0.0
  },
  {
    "Date":1706850000000,
    "Close":21.4954624176,
    "Dividends":0.0,
    "Stock Splits":0.0
  },
  {
    "Date":1707109200000,
    "Close":21.7482414246,
    "Dividends":0.0,
    "Stock Splits":0.0
  },
  {
    "Date":1707195600000,
    "Close":21.9635696411,
    "Dividends":0.0,
    "Stock Splits":0.0
  },
  {
    "Date":1707282000000,
    "Close":21.7950534821,
    "Dividends":0.0,
    "Stock Splits":0.0
  },
  {
    "Date":1707368400000,
    "Close":22.4597625732,
    "Dividends":0.0,
    "Stock Splits":0.0
  },
  {
    "Date":1707454800000,
    "Close":22.403591156,
    "Dividends":0.0,
    "Stock Splits":0.0
  },
  {
    "Date":1707714000000,
    "Close":22.8623371124,
    "Dividends":0.0,
    "Stock Splits":0.0
  },
  {
    "Date":1707800400000,
    "Close":22.8716964722,
    "Dividends":0.0,
    "Stock Splits":0.0
  },
  {
    "Date":1707886800000,
    "Close":22.4691257477,
    "Dividends":0.0,
    "Stock Splits":0.0
  },
  {
    "Date":1707973200000,
    "Close":22.79255867,
    "Dividends":0.38,
    "Stock Splits":0.0
  },
  {
    "Date":1708059600000,
    "Close":23.0018405914,
    "Dividends":0.0,
    "Stock Splits":0.0
  },
  {
    "Date":1708405200000,
    "Close":23.6106567383,
    "Dividends":0.0,
    "Stock Splits":0.0
  },
  {
    "Date":1708491600000,
    "Close":23.8675003052,
    "Dividends":0.0,
    "Stock Splits":0.0
  },
  {
    "Date":1708578000000,
    "Close":24.1243457794,
    "Dividends":0.0,
    "Stock Splits":0.0
  },
  {
    "Date":1708664400000,
    "Close":24.1814193726,
    "Dividends":0.0,
    "Stock Splits":0.0
  },
  {
    "Date":1708923600000,
    "Close":23.696269989,
    "Dividends":0.0,
    "Stock Splits":0.0
  },
  {
    "Date":1709010000000,
    "Close":23.6106567383,
    "Dividends":0.0,
    "Stock Splits":0.0
  },
  {
    "Date":1709096400000,
    "Close":23.5630931854,
    "Dividends":0.0,
    "Stock Splits":0.0
  },
  {
    "Date":1709182800000,
    "Close":24.2575244904,
    "Dividends":0.0,
    "Stock Splits":0.0
  },
  {
    "Date":1709269200000,
    "Close":24.7331619263,
    "Dividends":0.0,
    "Stock Splits":0.0
  },
  {
    "Date":1709528400000,
    "Close":25.2468509674,
    "Dividends":0.0,
    "Stock Splits":0.0
  },
  {
    "Date":1709614800000,
    "Close":25.4466171265,
    "Dividends":0.0,
    "Stock Splits":0.0
  },
  {
    "Date":1709701200000,
    "Close":25.3610019684,
    "Dividends":0.0,
    "Stock Splits":0.0
  },
  {
    "Date":1709787600000,
    "Close":23.9055500031,
    "Dividends":0.0,
    "Stock Splits":0.0
  },
  {
    "Date":1709874000000,
    "Close":24.2575244904,
    "Dividends":0.0,
    "Stock Splits":0.0
  },
  {
    "Date":1710129600000,
    "Close":24.2860622406,
    "Dividends":0.0,
    "Stock Splits":0.0
  },
  {
    "Date":1710216000000,
    "Close":24.2860622406,
    "Dividends":0.0,
    "Stock Splits":0.0
  },
  {
    "Date":1710302400000,
    "Close":24.5619297028,
    "Dividends":0.0,
    "Stock Splits":0.0
  },
  {
    "Date":1710388800000,
    "Close":25.0946464539,
    "Dividends":0.0,
    "Stock Splits":0.0
  },
  {
    "Date":1710475200000,
    "Close":24.8948783875,
    "Dividends":0.0,
    "Stock Splits":0.0
  },
  {
    "Date":1710734400000,
    "Close":24.8568267822,
    "Dividends":0.0,
    "Stock Splits":0.0
  },
  {
    "Date":1710820800000,
    "Close":25.2849006653,
    "Dividends":0.0,
    "Stock Splits":0.0
  },
  {
    "Date":1710907200000,
    "Close":25.5417461395,
    "Dividends":0.0,
    "Stock Splits":0.0
  },
  {
    "Date":1710993600000,
    "Close":26.1505622864,
    "Dividends":0.0,
    "Stock Splits":0.0
  },
  {
    "Date":1711080000000,
    "Close":25.61784935,
    "Dividends":0.0,
    "Stock Splits":0.0
  },
  {
    "Date":1711339200000,
    "Close":25.7224884033,
    "Dividends":0.0,
    "Stock Splits":0.0
  },
  {
    "Date":1711425600000,
    "Close":25.0946464539,
    "Dividends":0.0,
    "Stock Splits":0.0
  },
  {
    "Date":1711512000000,
    "Close":25.1517238617,
    "Dividends":0.0,
    "Stock Splits":0.0
  },
  {
    "Date":1711598400000,
    "Close":26.0078716278,
    "Dividends":0.0,
    "Stock Splits":0.0
  },
  {
    "Date":1711944000000,
    "Close":26.3693561554,
    "Dividends":0.0,
    "Stock Splits":0.0
  },
  {
    "Date":1712030400000,
    "Close":27.4157581329,
    "Dividends":0.0,
    "Stock Splits":0.0
  },
  {
    "Date":1712116800000,
    "Close":26.0173854828,
    "Dividends":0.0,
    "Stock Splits":0.0
  },
  {
    "Date":1712203200000,
    "Close":26.5691223145,
    "Dividends":0.0,
    "Stock Splits":0.0
  },
  {
    "Date":1712289600000,
    "Close":26.7498645782,
    "Dividends":0.0,
    "Stock Splits":0.0
  },
  {
    "Date":1712548800000,
    "Close":26.4074058533,
    "Dividends":0.0,
    "Stock Splits":0.0
  },
  {
    "Date":1712635200000,
    "Close":26.0744590759,
    "Dividends":0.0,
    "Stock Splits":0.0
  },
  {
    "Date":1712721600000,
    "Close":26.1220245361,
    "Dividends":0.0,
    "Stock Splits":0.0
  },
  {
    "Date":1712808000000,
    "Close":26.1410484314,
    "Dividends":0.0,
    "Stock Splits":0.0
  },
  {
    "Date":1712894400000,
    "Close":25.61784935,
    "Dividends":0.0,
    "Stock Splits":0.0
  },
  {
    "Date":1713153600000,
    "Close":25.3324642181,
    "Dividends":0.0,
    "Stock Splits":0.0
  },
  {
    "Date":1713240000000,
    "Close":25.256362915,
    "Dividends":0.0,
    "Stock Splits":0.0
  },
  {
    "Date":1713326400000,
    "Close":24.8663387299,
    "Dividends":0.0,
    "Stock Splits":0.0
  },
  {
    "Date":1713412800000,
    "Close":25.170747757,
    "Dividends":0.0,
    "Stock Splits":0.0
  },
  {
    "Date":1713499200000,
    "Close":25.6939506531,
    "Dividends":0.0,
    "Stock Splits":0.0
  },
  {
    "Date":1713758400000,
    "Close":26.2076358795,
    "Dividends":0.0,
    "Stock Splits":0.0
  },
  {
    "Date":1713844800000,
    "Close":26.3693561554,
    "Dividends":0.0,
    "Stock Splits":0.0
  },
  {
    "Date":1713931200000,
    "Close":26.2361774445,
    "Dividends":0.0,
    "Stock Splits":0.0
  },
  {
    "Date":1714017600000,
    "Close":26.2647151947,
    "Dividends":0.0,
    "Stock Splits":0.0
  },
  {
    "Date":1714104000000,
    "Close":26.5310726166,
    "Dividends":0.0,
    "Stock Splits":0.0
  },
  {
    "Date":1714363200000,
    "Close":26.3217906952,
    "Dividends":0.0,
    "Stock Splits":0.0
  },
  {
    "Date":1714449600000,
    "Close":25.8556671143,
    "Dividends":0.0,
    "Stock Splits":0.0
  },
  {
    "Date":1714536000000,
    "Close":25.0756225586,
    "Dividends":0.0,
    "Stock Splits":0.0
  },
  {
    "Date":1714622400000,
    "Close":25.6844367981,
    "Dividends":0.0,
    "Stock Splits":0.0
  },
  {
    "Date":1714708800000,
    "Close":25.9698200226,
    "Dividends":0.0,
    "Stock Splits":0.0
  },
  {
    "Date":1714968000000,
    "Close":26.1220245361,
    "Dividends":0.0,
    "Stock Splits":0.0
  },
  {
    "Date":1715054400000,
    "Close":26.6071720123,
    "Dividends":0.0,
    "Stock Splits":0.0
  },
  {
    "Date":1715140800000,
    "Close":26.6166877747,
    "Dividends":0.0,
    "Stock Splits":0.0
  },
  {
    "Date":1715227200000,
    "Close":26.8830451965,
    "Dividends":0.0,
    "Stock Splits":0.0
  },
  {
    "Date":1715313600000,
    "Close":26.690196991,
    "Dividends":0.38,
    "Stock Splits":0.0
  },
  {
    "Date":1715572800000,
    "Close":26.1405792236,
    "Dividends":0.0,
    "Stock Splits":0.0
  },
  {
    "Date":1715659200000,
    "Close":27.1337451935,
    "Dividends":0.0,
    "Stock Splits":0.0
  },
  {
    "Date":1715745600000,
    "Close":27.018037796,
    "Dividends":0.0,
    "Stock Splits":0.0
  },
  {
    "Date":1715832000000,
    "Close":27.2976665497,
    "Dividends":0.0,
    "Stock Splits":0.0
  },
  {
    "Date":1715918400000,
    "Close":27.4712314606,
    "Dividends":0.0,
    "Stock Splits":0.0
  },
  {
    "Date":1716177600000,
    "Close":27.9244232178,
    "Dividends":0.0,
    "Stock Splits":0.0
  },
  {
    "Date":1716264000000,
    "Close":27.5676555634,
    "Dividends":0.0,
    "Stock Splits":0.0
  },
  {
    "Date":1716350400000,
    "Close":26.3912830353,
    "Dividends":0.0,
    "Stock Splits":0.0
  },
  {
    "Date":1716436800000,
    "Close":26.0055847168,
    "Dividends":0.0,
    "Stock Splits":0.0
  },
  {
    "Date":1716523200000,
    "Close":25.7645244598,
    "Dividends":0.0,
    "Stock Splits":0.0
  },
  {
    "Date":1716868800000,
    "Close":25.7645244598,
    "Dividends":0.0,
    "Stock Splits":0.0
  },
  {
    "Date":1716955200000,
    "Close":25.4656085968,
    "Dividends":0.0,
    "Stock Splits":0.0
  },
  {
    "Date":1717041600000,
    "Close":25.6006031036,
    "Dividends":0.0,
    "Stock Splits":0.0
  },
  {
    "Date":1717128000000,
    "Close":26.5648422241,
    "Dividends":0.0,
    "Stock Splits":0.0
  },
  {
    "Date":1717387200000,
    "Close":25.8127346039,
    "Dividends":0.0,
    "Stock Splits":0.0
  },
  {
    "Date":1717473600000,
    "Close":25.3209724426,
    "Dividends":0.0,
    "Stock Splits":0.0
  },
  {
    "Date":1717560000000,
    "Close":25.3981132507,
    "Dividends":0.0,
    "Stock Splits":0.0
  },
  {
    "Date":1717646400000,
    "Close":25.041343689,
    "Dividends":0.0,
    "Stock Splits":0.0
  },
  {
    "Date":1717732800000,
    "Close":24.7713565826,
    "Dividends":0.0,
    "Stock Splits":0.0
  },
  {
    "Date":1717992000000,
    "Close":25.4559669495,
    "Dividends":0.0,
    "Stock Splits":0.0
  },
  {
    "Date":1718078400000,
    "Close":25.1763401031,
    "Dividends":0.0,
    "Stock Splits":0.0
  },
  {
    "Date":1718164800000,
    "Close":25.2052631378,
    "Dividends":0.0,
    "Stock Splits":0.0
  },
  {
    "Date":1718251200000,
    "Close":25.3113307953,
    "Dividends":0.0,
    "Stock Splits":0.0
  },
  {
    "Date":1718337600000,
    "Close":25.0606269836,
    "Dividends":0.0,
    "Stock Splits":0.0
  },
  {
    "Date":1718596800000,
    "Close":25.1281242371,
    "Dividends":0.0,
    "Stock Splits":0.0
  },
  {
    "Date":1718683200000,
    "Close":25.2341918945,
    "Dividends":0.0,
    "Stock Splits":0.0
  },
  {
    "Date":1718856000000,
    "Close":25.1184806824,
    "Dividends":0.0,
    "Stock Splits":0.0
  },
  {
    "Date":1718942400000,
    "Close":25.1666946411,
    "Dividends":0.0,
    "Stock Splits":0.0
  },
  {
    "Date":1719201600000,
    "Close":25.7838096619,
    "Dividends":0.0,
    "Stock Splits":0.0
  },
  {
    "Date":1719288000000,
    "Close":25.6970272064,
    "Dividends":0.0,
    "Stock Splits":0.0
  },
  {
    "Date":1719374400000,
    "Close":25.9863014221,
    "Dividends":0.0,
    "Stock Splits":0.0
  },
  {
    "Date":1719460800000,
    "Close":25.928445816,
    "Dividends":0.0,
    "Stock Splits":0.0
  },
  {
    "Date":1719547200000,
    "Close":26.2852134705,
    "Dividends":0.0,
    "Stock Splits":0.0
  },
  {
    "Date":1719806400000,
    "Close":26.1405792236,
    "Dividends":0.0,
    "Stock Splits":0.0
  },
  {
    "Date":1719892800000,
    "Close":26.2562866211,
    "Dividends":0.0,
    "Stock Splits":0.0
  },
  {
    "Date":1719979200000,
    "Close":26.9023284912,
    "Dividends":0.0,
    "Stock Splits":0.0
  },
  {
    "Date":1720152000000,
    "Close":26.0827217102,
    "Dividends":0.0,
    "Stock Splits":0.0
  },
  {
    "Date":1720411200000,
    "Close":25.7163124084,
    "Dividends":0.0,
    "Stock Splits":0.0
  },
  {
    "Date":1720497600000,
    "Close":24.9738483429,
    "Dividends":0.0,
    "Stock Splits":0.0
  },
  {
    "Date":1720584000000,
    "Close":26.0055847168,
    "Dividends":0.0,
    "Stock Splits":0.0
  },
  {
    "Date":1720670400000,
    "Close":26.4009208679,
    "Dividends":0.0,
    "Stock Splits":0.0
  },
  {
    "Date":1720756800000,
    "Close":26.3719978333,
    "Dividends":0.0,
    "Stock Splits":0.0
  },
  {
    "Date":1721016000000,
    "Close":27.5869407654,
    "Dividends":0.0,
    "Stock Splits":0.0
  },
  {
    "Date":1721102400000,
    "Close":27.5098018646,
    "Dividends":0.0,
    "Stock Splits":0.0
  },
  {
    "Date":1721188800000,
    "Close":27.9629936218,
    "Dividends":0.0,
    "Stock Splits":0.0
  },
  {
    "Date":1721275200000,
    "Close":28.0401344299,
    "Dividends":0.0,
    "Stock Splits":0.0
  },
  {
    "Date":1721361600000,
    "Close":27.2494564056,
    "Dividends":0.0,
    "Stock Splits":0.0
  },
  {
    "Date":1721620800000,
    "Close":27.6158676147,
    "Dividends":0.0,
    "Stock Splits":0.0
  },
  {
    "Date":1721707200000,
    "Close":27.0469646454,
    "Dividends":0.0,
    "Stock Splits":0.0
  },
  {
    "Date":1721793600000,
    "Close":26.6323413849,
    "Dividends":0.0,
    "Stock Splits":0.0
  },
  {
    "Date":1721880000000,
    "Close":25.8030948639,
    "Dividends":0.0,
    "Stock Splits":0.0
  },
  {
    "Date":1721966400000,
    "Close":26.8541164398,
    "Dividends":0.0,
    "Stock Splits":0.0
  },
  {
    "Date":1722225600000,
    "Close":26.6805534363,
    "Dividends":0.0,
    "Stock Splits":0.0
  },
  {
    "Date":1722312000000,
    "Close":27.3169517517,
    "Dividends":0.0,
    "Stock Splits":0.0
  },
  {
    "Date":1722398400000,
    "Close":27.818359375,
    "Dividends":0.0,
    "Stock Splits":0.0
  },
  {
    "Date":1722484800000,
    "Close":26.8830432892,
    "Dividends":0.0,
    "Stock Splits":0.0
  },
  {
    "Date":1722571200000,
    "Close":25.9188022614,
    "Dividends":0.0,
    "Stock Splits":0.0
  },
  {
    "Date":1722830400000,
    "Close":25.359544754,
    "Dividends":0.0,
    "Stock Splits":0.0
  },
  {
    "Date":1722916800000,
    "Close":25.889875412,
    "Dividends":0.0,
    "Stock Splits":0.0
  },
  {
    "Date":1723003200000,
    "Close":26.188791275,
    "Dividends":0.0,
    "Stock Splits":0.0
  },
  {
    "Date":1723089600000,
    "Close":27.9726371765,
    "Dividends":0.0,
    "Stock Splits":0.0
  },
  {
    "Date":1723176000000,
    "Close":27.847284317,
    "Dividends":0.0,
    "Stock Splits":0.0
  },
  {
    "Date":1723435200000,
    "Close":28.6689128876,
    "Dividends":0.41,
    "Stock Splits":0.0
  },
  {
    "Date":1723521600000,
    "Close":25.5291233063,
    "Dividends":0.0,
    "Stock Splits":0.0
  },
  {
    "Date":1723608000000,
    "Close":25.0400600433,
    "Dividends":0.0,
    "Stock Splits":0.0
  },
  {
    "Date":1723694400000,
    "Close":25.7345294952,
    "Dividends":0.0,
    "Stock Splits":0.0
  },
  {
    "Date":1723780800000,
    "Close":25.6464977264,
    "Dividends":0.0,
    "Stock Splits":0.0
  },
  {
    "Date":1724040000000,
    "Close":25.4313106537,
    "Dividends":0.0,
    "Stock Splits":0.0
  },
  {
    "Date":1724126400000,
    "Close":25.2943725586,
    "Dividends":0.0,
    "Stock Splits":0.0
  },
  {
    "Date":1724212800000,
    "Close":25.9790611267,
    "Dividends":0.0,
    "Stock Splits":0.0
  },
  {
    "Date":1724299200000,
    "Close":25.5291233063,
    "Dividends":0.0,
    "Stock Splits":0.0
  },
  {
    "Date":1724385600000,
    "Close":26.6050643921,
    "Dividends":0.0,
    "Stock Splits":0.0
  },
  {
    "Date":1724644800000,
    "Close":26.8300323486,
    "Dividends":0.0,
    "Stock Splits":0.0
  },
  {
    "Date":1724731200000,
    "Close":26.732219696,
    "Dividends":0.0,
    "Stock Splits":0.0
  },
  {
    "Date":1724817600000,
    "Close":26.5268135071,
    "Dividends":0.0,
    "Stock Splits":0.0
  },
  {
    "Date":1724904000000,
    "Close":27.0256576538,
    "Dividends":0.0,
    "Stock Splits":0.0
  },
  {
    "Date":1724990400000,
    "Close":27.1430339813,
    "Dividends":0.0,
    "Stock Splits":0.0
  },
  {
    "Date":1725336000000,
    "Close":25.3824043274,
    "Dividends":0.0,
    "Stock Splits":0.0
  },
  {
    "Date":1725422400000,
    "Close":25.3726234436,
    "Dividends":0.0,
    "Stock Splits":0.0
  },
  {
    "Date":1725508800000,
    "Close":26.0866565704,
    "Dividends":0.0,
    "Stock Splits":0.0
  },
  {
    "Date":1725595200000,
    "Close":26.0475292206,
    "Dividends":0.0,
    "Stock Splits":0.0
  },
  {
    "Date":1725854400000,
    "Close":24.6781520844,
    "Dividends":0.0,
    "Stock Splits":0.0
  },
  {
    "Date":1725940800000,
    "Close":25.7345294952,
    "Dividends":0.0,
    "Stock Splits":0.0
  },
  {
    "Date":1726027200000,
    "Close":25.6758441925,
    "Dividends":0.0,
    "Stock Splits":0.0
  },
  {
    "Date":1726113600000,
    "Close":25.6660614014,
    "Dividends":0.0,
    "Stock Splits":0.0
  },
  {
    "Date":1726200000000,
    "Close":26.0866565704,
    "Dividends":0.0,
    "Stock Splits":0.0
  },
  {
    "Date":1726459200000,
    "Close":26.340970993,
    "Dividends":0.0,
    "Stock Splits":0.0
  },
  {
    "Date":1726545600000,
    "Close":27.299533844,
    "Dividends":0.0,
    "Stock Splits":0.0
  },
  {
    "Date":1726632000000,
    "Close":28.0429115295,
    "Dividends":0.0,
    "Stock Splits":0.0
  },
  {
    "Date":1726718400000,
    "Close":28.8841018677,
    "Dividends":0.0,
    "Stock Splits":0.0
  },
  {
    "Date":1726804800000,
    "Close":28.9330062866,
    "Dividends":0.0,
    "Stock Splits":0.0
  },
  {
    "Date":1727064000000,
    "Close":28.9916934967,
    "Dividends":0.0,
    "Stock Splits":0.0
  },
  {
    "Date":1727150400000,
    "Close":28.8058509827,
    "Dividends":0.0,
    "Stock Splits":0.0
  },
  {
    "Date":1727236800000,
    "Close":28.7960681915,
    "Dividends":0.0,
    "Stock Splits":0.0
  },
  {
    "Date":1727323200000,
    "Close":28.1211624146,
    "Dividends":0.0,
    "Stock Splits":0.0
  },
  {
    "Date":1727409600000,
    "Close":28.6004428864,
    "Dividends":0.0,
    "Stock Splits":0.0
  },
  {
    "Date":1727668800000,
    "Close":28.3656921387,
    "Dividends":0.0,
    "Stock Splits":0.0
  },
  {
    "Date":1727755200000,
    "Close":28.5710983276,
    "Dividends":0.0,
    "Stock Splits":0.0
  },
  {
    "Date":1727841600000,
    "Close":29.2655696869,
    "Dividends":0.0,
    "Stock Splits":0.0
  },
  {
    "Date":1727928000000,
    "Close":29.8915729523,
    "Dividends":0.0,
    "Stock Splits":0.0
  },
  {
    "Date":1728014400000,
    "Close":31.7891387939,
    "Dividends":0.0,
    "Stock Splits":0.0
  },
  {
    "Date":1728273600000,
    "Close":31.4272327423,
    "Dividends":0.0,
    "Stock Splits":0.0
  },
  {
    "Date":1728360000000,
    "Close":30.4099788666,
    "Dividends":0.0,
    "Stock Splits":0.0
  },
  {
    "Date":1728446400000,
    "Close":31.2609500885,
    "Dividends":0.0,
    "Stock Splits":0.0
  },
  {
    "Date":1728532800000,
    "Close":31.485918045,
    "Dividends":0.0,
    "Stock Splits":0.0
  },
  {
    "Date":1728619200000,
    "Close":31.6130752563,
    "Dividends":0.0,
    "Stock Splits":0.0
  },
  {
    "Date":1728878400000,
    "Close":31.1044502258,
    "Dividends":0.0,
    "Stock Splits":0.0
  },
  {
    "Date":1728964800000,
    "Close":30.3610744476,
    "Dividends":0.0,
    "Stock Splits":0.0
  },
  {
    "Date":1729051200000,
    "Close":30.7034168243,
    "Dividends":0.0,
    "Stock Splits":0.0
  },
  {
    "Date":1729137600000,
    "Close":30.7034168243,
    "Dividends":0.0,
    "Stock Splits":0.0
  },
  {
    "Date":1729224000000,
    "Close":30.4393253326,
    "Dividends":0.0,
    "Stock Splits":0.0
  },
  {
    "Date":1729483200000,
    "Close":30.2241344452,
    "Dividends":0.0,
    "Stock Splits":0.0
  },
  {
    "Date":1729569600000,
    "Close":30.3806343079,
    "Dividends":0.0,
    "Stock Splits":0.0
  },
  {
    "Date":1729656000000,
    "Close":30.106760025,
    "Dividends":0.0,
    "Stock Splits":0.0
  },
  {
    "Date":1729742400000,
    "Close":30.0285110474,
    "Dividends":0.0,
    "Stock Splits":0.0
  },
  {
    "Date":1729828800000,
    "Close":30.674074173,
    "Dividends":0.0,
    "Stock Splits":0.0
  },
  {
    "Date":1730088000000,
    "Close":31.0066375732,
    "Dividends":0.0,
    "Stock Splits":0.0
  },
  {
    "Date":1730174400000,
    "Close":31.0261993408,
    "Dividends":0.0,
    "Stock Splits":0.0
  },
  {
    "Date":1730260800000,
    "Close":31.1142311096,
    "Dividends":0.0,
    "Stock Splits":0.0
  },
  {
    "Date":1730347200000,
    "Close":31.1826992035,
    "Dividends":0.0,
    "Stock Splits":0.0
  },
  {
    "Date":1730433600000,
    "Close":30.8458023071,
    "Dividends":0.41,
    "Stock Splits":0.0
  },
  {
    "Date":1730696400000,
    "Close":30.9151649475,
    "Dividends":0.0,
    "Stock Splits":0.0
  },
  {
    "Date":1730782800000,
    "Close":32.1933898926,
    "Dividends":0.0,
    "Stock Splits":0.0
  },
  {
    "Date":1730869200000,
    "Close":34.5120277405,
    "Dividends":0.0,
    "Stock Splits":0.0
  },
  {
    "Date":1730955600000,
    "Close":34.2345809937,
    "Dividends":0.0,
    "Stock Splits":0.0
  },
  {
    "Date":1731042000000,
    "Close":34.5120277405,
    "Dividends":0.0,
    "Stock Splits":0.0
  },
  {
    "Date":1731301200000,
    "Close":35.9686050415,
    "Dividends":0.0,
    "Stock Splits":0.0
  },
  {
    "Date":1731387600000,
    "Close":35.8397903442,
    "Dividends":0.0,
    "Stock Splits":0.0
  },
  {
    "Date":1731474000000,
    "Close":35.5227127075,
    "Dividends":0.0,
    "Stock Splits":0.0
  },
  {
    "Date":1731560400000,
    "Close":35.4731674194,
    "Dividends":0.0,
    "Stock Splits":0.0
  },
  {
    "Date":1731646800000,
    "Close":36.1073265076,
    "Dividends":0.0,
    "Stock Splits":0.0
  },
  {
    "Date":1731906000000,
    "Close":37.2567367554,
    "Dividends":0.0,
    "Stock Splits":0.0
  },
  {
    "Date":1731992400000,
    "Close":38.1187934875,
    "Dividends":0.0,
    "Stock Splits":0.0
  },
  {
    "Date":1732078800000,
    "Close":38.7430419922,
    "Dividends":0.0,
    "Stock Splits":0.0
  },
  {
    "Date":1732165200000,
    "Close":40.675239563,
    "Dividends":0.0,
    "Stock Splits":0.0
  },
  {
    "Date":1732251600000,
    "Close":40.0708084106,
    "Dividends":0.0,
    "Stock Splits":0.0
  },
  {
    "Date":1732510800000,
    "Close":39.357383728,
    "Dividends":0.0,
    "Stock Splits":0.0
  },
  {
    "Date":1732597200000,
    "Close":39.5456466675,
    "Dividends":0.0,
    "Stock Splits":0.0
  },
  {
    "Date":1732683600000,
    "Close":39.4564704895,
    "Dividends":0.0,
    "Stock Splits":0.0
  },
  {
    "Date":1732856400000,
    "Close":40.0708084106,
    "Dividends":0.0,
    "Stock Splits":0.0
  },
  {
    "Date":1733115600000,
    "Close":39.7933654785,
    "Dividends":0.0,
    "Stock Splits":0.0
  },
  {
    "Date":1733202000000,
    "Close":40.1203536987,
    "Dividends":0.0,
    "Stock Splits":0.0
  },
  {
    "Date":1733288400000,
    "Close":40.3284378052,
    "Dividends":0.0,
    "Stock Splits":0.0
  },
  {
    "Date":1733374800000,
    "Close":41.477848053,
    "Dividends":0.0,
    "Stock Splits":0.0
  },
  {
    "Date":1733461200000,
    "Close":40.7941436768,
    "Dividends":0.0,
    "Stock Splits":0.0
  },
  {
    "Date":1733720400000,
    "Close":41.1409492493,
    "Dividends":0.0,
    "Stock Splits":0.0
  },
  {
    "Date":1733806800000,
    "Close":41.2796707153,
    "Dividends":0.0,
    "Stock Splits":0.0
  },
  {
    "Date":1733893200000,
    "Close":43.1425094604,
    "Dividends":0.0,
    "Stock Splits":0.0
  },
  {
    "Date":1733979600000,
    "Close":41.1706733704,
    "Dividends":0.0,
    "Stock Splits":0.0
  },
  {
    "Date":1734066000000,
    "Close":40.6058807373,
    "Dividends":0.0,
    "Stock Splits":0.0
  },
  {
    "Date":1734325200000,
    "Close":41.1112251282,
    "Dividends":0.0,
    "Stock Splits":0.0
  },
  {
    "Date":1734411600000,
    "Close":40.7445983887,
    "Dividends":0.0,
    "Stock Splits":0.0
  },
  {
    "Date":1734498000000,
    "Close":38.2376976013,
    "Dividends":0.0,
    "Stock Splits":0.0
  },
  {
    "Date":1734584400000,
    "Close":38.5845031738,
    "Dividends":0.0,
    "Stock Splits":0.0
  },
  {
    "Date":1734670800000,
    "Close":39.4366531372,
    "Dividends":0.0,
    "Stock Splits":0.0
  },
  {
    "Date":1734930000000,
    "Close":39.694278717,
    "Dividends":0.0,
    "Stock Splits":0.0
  },
  {
    "Date":1735016400000,
    "Close":40.427520752,
    "Dividends":0.0,
    "Stock Splits":0.0
  },
  {
    "Date":1735189200000,
    "Close":40.5365180969,
    "Dividends":0.0,
    "Stock Splits":0.0
  },
  {
    "Date":1735275600000,
    "Close":40.0807189941,
    "Dividends":0.0,
    "Stock Splits":0.0
  },
  {
    "Date":1735534800000,
    "Close":40.5464248657,
    "Dividends":0.0,
    "Stock Splits":0.0
  },
  {
    "Date":1735621200000,
    "Close":40.4572525024,
    "Dividends":0.0,
    "Stock Splits":0.0
  },
  {
    "Date":1735794000000,
    "Close":41.3886680603,
    "Dividends":0.0,
    "Stock Splits":0.0
  },
  {
    "Date":1735880400000,
    "Close":43.2614135742,
    "Dividends":0.0,
    "Stock Splits":0.0
  },
  {
    "Date":1736139600000,
    "Close":43.1722335815,
    "Dividends":0.0,
    "Stock Splits":0.0
  },
  {
    "Date":1736226000000,
    "Close":42.0030059814,
    "Dividends":0.0,
    "Stock Splits":0.0
  },
  {
    "Date":1736312400000,
    "Close":41.2994880676,
    "Dividends":0.0,
    "Stock Splits":0.0
  },
  {
    "Date":1736485200000,
    "Close":41.6165657043,
    "Dividends":0.0,
    "Stock Splits":0.0
  },
  {
    "Date":1736744400000,
    "Close":42.4290809631,
    "Dividends":0.0,
    "Stock Splits":0.0
  },
  {
    "Date":1736830800000,
    "Close":44.9954376221,
    "Dividends":0.0,
    "Stock Splits":0.0
  },
  {
    "Date":1736917200000,
    "Close":45.7286834717,
    "Dividends":0.0,
    "Stock Splits":0.0
  },
  {
    "Date":1737003600000,
    "Close":46.620464325,
    "Dividends":0.0,
    "Stock Splits":0.0
  },
  {
    "Date":1737090000000,
    "Close":46.9474525452,
    "Dividends":0.0,
    "Stock Splits":0.0
  },
  {
    "Date":1737435600000,
    "Close":48.5130271912,
    "Dividends":0.0,
    "Stock Splits":0.0
  },
  {
    "Date":1737522000000,
    "Close":48.3743057251,
    "Dividends":0.0,
    "Stock Splits":0.0
  },
  {
    "Date":1737608400000,
    "Close":48.3544883728,
    "Dividends":0.0,
    "Stock Splits":0.0
  },
  {
    "Date":1737694800000,
    "Close":49.1570930481,
    "Dividends":0.0,
    "Stock Splits":0.0
  },
  {
    "Date":1737954000000,
    "Close":43.5983085632,
    "Dividends":0.0,
    "Stock Splits":0.0
  },
  {
    "Date":1738040400000,
    "Close":47.3239822388,
    "Dividends":0.0,
    "Stock Splits":0.0
  },
  {
    "Date":1738126800000,
    "Close":47.6113357544,
    "Dividends":0.0,
    "Stock Splits":0.0
  },
  {
    "Date":1738213200000,
    "Close":49.2066383362,
    "Dividends":0.0,
    "Stock Splits":0.0
  },
  {
    "Date":1738299600000,
    "Close":46.3529281616,
    "Dividends":0.0,
    "Stock Splits":0.0
  },
  {
    "Date":1738558800000,
    "Close":46.9078178406,
    "Dividends":0.0,
    "Stock Splits":0.0
  },
  {
    "Date":1738645200000,
    "Close":46.5213775635,
    "Dividends":0.0,
    "Stock Splits":0.0
  },
  {
    "Date":1738731600000,
    "Close":47.2645301819,
    "Dividends":0.0,
    "Stock Splits":0.0
  },
  {
    "Date":1738818000000,
    "Close":45.9565811157,
    "Dividends":0.0,
    "Stock Splits":0.0
  },
  {
    "Date":1738904400000,
    "Close":44.8666229248,
    "Dividends":0.0,
    "Stock Splits":0.0
  },
  {
    "Date":1739163600000,
    "Close":45.7484970093,
    "Dividends":0.0,
    "Stock Splits":0.0
  },
  {
    "Date":1739250000000,
    "Close":44.8864402771,
    "Dividends":0.0,
    "Stock Splits":0.0
  },
  {
    "Date":1739336400000,
    "Close":44.0342903137,
    "Dividends":0.0,
    "Stock Splits":0.0
  },
  {
    "Date":1739422800000,
    "Close":44.5,
    "Dividends":0.0,
    "Stock Splits":0.0
  },
  {
    "Date":1739509200000,
    "Close":45.2999992371,
    "Dividends":0.41,
    "Stock Splits":0.0
  },
  {
    "Date":1739854800000,
    "Close":45.9199981689,
    "Dividends":0.0,
    "Stock Splits":0.0
  },
  {
    "Date":1739941200000,
    "Close":46.6399993896,
    "Dividends":0.0,
    "Stock Splits":0.0
  },
  {
    "Date":1740027600000,
    "Close":45.0600013733,
    "Dividends":0.0,
    "Stock Splits":0.0
  },
  {
    "Date":1740114000000,
    "Close":43.7000007629,
    "Dividends":0.0,
    "Stock Splits":0.0
  },
  {
    "Date":1740373200000,
    "Close":42.3600006104,
    "Dividends":0.0,
    "Stock Splits":0.0
  },
  {
    "Date":1740459600000,
    "Close":42.0299987793,
    "Dividends":0.0,
    "Stock Splits":0.0
  },
  {
    "Date":1740546000000,
    "Close":43.0,
    "Dividends":0.0,
    "Stock Splits":0.0
  },
  {
    "Date":1740632400000,
    "Close":42.4099998474,
    "Dividends":0.0,
    "Stock Splits":0.0
  },
  {
    "Date":1740718800000,
    "Close":43.0,
    "Dividends":0.0,
    "Stock Splits":0.0
  },
  {
    "Date":1740978000000,
    "Close":41.0400009155,
    "Dividends":0.0,
    "Stock Splits":0.0
  },
  {
    "Date":1741064400000,
    "Close":39.8600006104,
    "Dividends":0.0,
    "Stock Splits":0.0
  },
  {
    "Date":1741150800000,
    "Close":40.5600013733,
    "Dividends":0.0,
    "Stock Splits":0.0
  },
  {
    "Date":1741237200000,
    "Close":34.4799995422,
    "Dividends":0.0,
    "Stock Splits":0.0
  },
  {
    "Date":1741323600000,
    "Close":34.0800018311,
    "Dividends":0.0,
    "Stock Splits":0.0
  },
  {
    "Date":1741579200000,
    "Close":33.2599983215,
    "Dividends":0.0,
    "Stock Splits":0.0
  },
  {
    "Date":1741665600000,
    "Close":35.2999992371,
    "Dividends":0.0,
    "Stock Splits":0.0
  },
  {
    "Date":1741752000000,
    "Close":37.0099983215,
    "Dividends":0.0,
    "Stock Splits":0.0
  },
  {
    "Date":1741838400000,
    "Close":36.0900001526,
    "Dividends":0.0,
    "Stock Splits":0.0
  },
  {
    "Date":1741924800000,
    "Close":36.7999992371,
    "Dividends":0.0,
    "Stock Splits":0.0
  },
  {
    "Date":1742184000000,
    "Close":38.2400016785,
    "Dividends":0.0,
    "Stock Splits":0.0
  },
  {
    "Date":1742270400000,
    "Close":37.5800018311,
    "Dividends":0.0,
    "Stock Splits":0.0
  },
  {
    "Date":1742356800000,
    "Close":38.8199996948,
    "Dividends":0.0,
    "Stock Splits":0.0
  },
  {
    "Date":1742443200000,
    "Close":38.4500007629,
    "Dividends":0.0,
    "Stock Splits":0.0
  },
  {
    "Date":1742529600000,
    "Close":37.7999992371,
    "Dividends":0.0,
    "Stock Splits":0.0
  },
  {
    "Date":1742788800000,
    "Close":39.2299995422,
    "Dividends":0.0,
    "Stock Splits":0.0
  }
]